texet/__init__.py
texet/main.py
texet/.system/imports.py
texet/.system/index.py
texet/.system/modules/ai.py
texet/.system/modules/speak.py
texet/.system/sources/clight.json
texet/.system/sources/ext.yml
texet/.system/sources/lng.yml
texet/.system/sources/logo.ico
texet-1.3.0.dist-info/licenses/LICENSE
texet-1.3.0.dist-info/METADATA
texet-1.3.0.dist-info/WHEEL
texet-1.3.0.dist-info/entry_points.txt
texet-1.3.0.dist-info/top_level.txt
texet-1.3.0.dist-info/RECORD
