Metadata-Version: 2.4
Name: texet
Version: 1.3.0
Summary: TexeT is the tool you need to take your interaction and content control to the next level
Home-page: https://github.com/IG-onGit/TexeT
Author: Irakli Gzirishvili
Author-email: gziraklirex@gmail.com
Classifier: Programming Language :: Python :: 3
Classifier: License :: OSI Approved :: MIT License
Classifier: Operating System :: OS Independent
License-File: LICENSE
Requires-Dist: clight
Requires-Dist: openai
Requires-Dist: keyboard
Requires-Dist: pyautogui
Requires-Dist: pyperclip
Requires-Dist: googletrans
Dynamic: author
Dynamic: author-email
Dynamic: classifier
Dynamic: description
Dynamic: description-content-type
Dynamic: home-page
Dynamic: license-file
Dynamic: requires-dist
Dynamic: summary
